{
    "name": "Tristan",
    "class": "TRAINER_CLASS_YOUNGSTER",
    "items": [],
    "ai_flags": [
        "AI_FLAG_BASIC"
    ],
    "double_battle": false,
    "party": [
        {
            "species": "SPECIES_BIDOOF",
            "form": 0,
            "level": 7,
            "item": "ITEM_BERRY_JUICE",
            "moves": [
                "MOVE_THUNDERBOLT",
                "MOVE_CHARGE_BEAM"
            ],
            "abilitySlot": 0,
            "nature": 10,
            "status": 0,
            "gender": 3,
            "ivs": 0,
            "preDamage": 0,
            "ball_seal": 0
        },
        {
            "species": "SPECIES_ZIGZAGOON",
            "form": 0,
            "level": 7,
            "item": "ITEM_STARF_BERRY",
            "moves": [
                "MOVE_ICE_BEAM"
            ],
            "abilitySlot": 0,
            "nature": 15,
            "status": 2,
            "gender": 3,
            "ivs": 0,
            "preDamage": 0,
            "ball_seal": 0
        },
        {
            "species": "SPECIES_AIPOM",
            "form": 0,
            "level": 7,
            "item": "ITEM_CHOPLE_BERRY",
            "moves": [
                "MOVE_PAYBACK"
            ],
            "abilitySlot": 0,
            "nature": 3,
            "status": 0,
            "gender": 3,
            "ivs": 0,
            "preDamage": 0,
            "ball_seal": 0
        }
    ]
}