{
    "base_stats": {
        "hp": 58,
        "attack": 64,
        "defense": 58,
        "speed": 80,
        "special_attack": 80,
        "special_defense": 65
    },
    "types": [
        "TYPE_FIRE",
        "TYPE_FIRE"
    ],
    "catch_rate": 45,
    "base_exp_reward": 142,
    "ev_yields": {
        "hp": 0,
        "attack": 0,
        "defense": 0,
        "speed": 0,
        "special_attack": 0,
        "special_defense": 0
    },
    "held_items": {
        "common": "ITEM_NONE",
        "rare": "ITEM_NONE"
    },
    "gender_ratio": "GENDER_RATIO_FEMALE_12_5",
    "hatch_cycles": 20,
    "base_friendship": 70,
    "exp_rate": "EXP_RATE_MEDIUM_SLOW",
    "egg_groups": [
        "EGG_GROUP_FIELD",
        "EGG_GROUP_FIELD"
    ],
    "abilities": [
        "ABILITY_BLAZE",
        "ABILITY_MOLD_BREAKER",
        "ABILITY_FLASH_FIRE"
    ],
    "safari_flee_rate": 0,
    "body_color": "MON_COLOR_YELLOW",
    "flip_sprite": false,
    "learnset": {
        "by_level": [],
        "by_tm": [],
        "by_tutor": []
    },
    "evolutions": [
        [
            "EVO_LEVEL",
            36,
            "SPECIES_TYPHLOSION"
        ]
    ],
    "footprint": {
        "has": true,
        "size": "FOOTPRINT_SMALL"
    },
    "pokedex_data": {
        "height": 9,
        "weight": 190,
        "body_shape": "SHAPE_QUADRUPED",
        "trainer_scale_f": 272,
        "pokemon_scale_f": 300,
        "trainer_scale_m": 256,
        "pokemon_scale_m": 300,
        "trainer_pos_f": 8,
        "pokemon_pos_f": 19,
        "trainer_pos_m": 9,
        "pokemon_pos_m": 19,
        "en": {
            "name": "QUILAVA",
            "category": "Volcano Pok\u00e9mon",
            "entry_text": [
                "It intimidates foes with the heat\n",
                "of its flames. The fire burns more\n",
                "strongly when it readies to fight."
            ]
        },
        "fr": {
            "name": "FEURISSON",
            "category": "Pok\u00e9mon Volcan",
            "entry_text": [
                "La chaleur de ses flammes intimide\n",
                "l\u2019ennemi. Elles s\u2019intensifient\n",
                "lorsqu\u2019il se pr\u00e9pare \u00e0 combattre."
            ]
        },
        "de": {
            "name": "IGELAVAR",
            "category": "Vulkan",
            "entry_text": [
                "Es bedroht seine Gegner mit der\n",
                "Hitze seiner Flammen. Ist es\n",
                "kampfbereit, lodern sie st\u00e4rker."
            ]
        },
        "it": {
            "name": "QUILAVA",
            "category": "Pok\u00e9mon Vulcano",
            "entry_text": [
                "Intimorisce i nemici con il calore\n",
                "delle sue fiamme. Se \u00e8 pronto a lot-\n",
                "tare, le vampate sono pi\u00f9 ardenti."
            ]
        },
        "es": {
            "name": "QUILAVA",
            "category": "Pok\u00e9mon Volc\u00e1n",
            "entry_text": [
                "Intimida a sus enemigos con el\n",
                "calor de sus llamas. Arde con\n",
                "mayor fuerza cuando va a luchar."
            ]
        },
        "jp": {
            "name": "\u30de\u30b0\u30de\u30e9\u30b7",
            "category": "\u304b\u3056\u3093\u30dd\u30b1\u30e2\u30f3",
            "entry_text": [
                "\u307b\u306e\u304a\u306e\u3000\u306d\u3064\u3067\u3000\u3042\u3044\u3066\u3092\u3000\u3044\u304b\u304f\u3002\n",
                "\u305f\u305f\u304b\u3046\u3000\u305f\u3044\u305b\u3044\u306b\u306a\u308b\u3068\n",
                "\u307b\u306e\u304a\u306e\u3000\u3044\u304d\u304a\u3044\u304c\u3000\u307e\u3059\u3002"
            ]
        }
    },
    "catching_show": {
        "pal_park_land_area": "PAL_PARK_AREA_LAND_SOUTH_WEST",
        "pal_park_water_area": "PAL_PARK_AREA_WATER_NONE",
        "catching_points": 80,
        "rarity": 10,
        "unused": 514
    }
}