{
    "base_stats": {
        "hp": 60,
        "attack": 60,
        "defense": 60,
        "speed": 30,
        "special_attack": 35,
        "special_defense": 35
    },
    "types": [
        "TYPE_NORMAL",
        "TYPE_NORMAL"
    ],
    "catch_rate": 255,
    "base_exp_reward": 83,
    "ev_yields": {
        "hp": 1,
        "attack": 0,
        "defense": 0,
        "speed": 0,
        "special_attack": 0,
        "special_defense": 0
    },
    "held_items": {
        "common": "ITEM_NONE",
        "rare": "ITEM_NONE"
    },
    "gender_ratio": "GENDER_RATIO_FEMALE_50",
    "hatch_cycles": 15,
    "base_friendship": 70,
    "exp_rate": "EXP_RATE_SLOW",
    "egg_groups": [
        "EGG_GROUP_FIELD",
        "EGG_GROUP_FIELD"
    ],
    "abilities": [
        "ABILITY_TRUANT",
        "ABILITY_NONE",
        "ABILITY_NONE"
    ],
    "safari_flee_rate": 0,
    "body_color": "MON_COLOR_BROWN",
    "flip_sprite": false,
    "learnset": {
        "by_level": [
            [
                1,
                "MOVE_SCRATCH"
            ],
            [
                1,
                "MOVE_YAWN"
            ],
            [
                7,
                "MOVE_ENCORE"
            ],
            [
                13,
                "MOVE_SLACK_OFF"
            ],
            [
                15,
                "MOVE_CRUSH_CLAW"
            ],
            [
                19,
                "MOVE_FAINT_ATTACK"
            ],
            [
                23,
                "MOVE_SLASH"
            ],
            [
                27,
                "MOVE_BRICK_BREAK"
            ],
            [
                30,
                "MOVE_BODY_SLAM"
            ],
            [
                32,
                "MOVE_NIGHT_SLASH"
            ],
            [
                37,
                "MOVE_COUNTER"
            ]
        ],
        "by_tm": [],
        "by_tutor": []
    },
    "evolutions": [
        [
            "EVO_LEVEL",
            20,
            "SPECIES_VIGOROTH"
        ]
    ],
    "footprint": {
        "has": true,
        "size": "FOOTPRINT_MEDIUM"
    },
    "pokedex_data": {
        "height": 8,
        "weight": 240,
        "body_shape": "SHAPE_QUADRUPED",
        "trainer_scale_f": 272,
        "pokemon_scale_f": 258,
        "trainer_scale_m": 256,
        "pokemon_scale_m": 281,
        "trainer_pos_f": 8,
        "pokemon_pos_f": 21,
        "trainer_pos_m": 9,
        "pokemon_pos_m": 22,
        "en": {
            "name": "SLAKOTH",
            "category": "Slacker Pok\u00e9mon",
            "entry_text": [
                "It spends nearly all its time in a\n",
                "day sprawled out. Just seeing it\n",
                "makes one drowsy."
            ]
        },
        "fr": {
            "name": "PARECOOL",
            "category": "Pok\u00e9mon Fl\u00e2neur",
            "entry_text": [
                "Il passe le plus clair de son temps\n",
                "affal\u00e9. Rien qu\u2019\u00e0 le voir, on a\n",
                "envie de b\u00e2iller."
            ]
        },
        "de": {
            "name": "BUMMELZ",
            "category": "Faulpelz",
            "entry_text": [
                "Es verbringt fast den ganzen Tag\n",
                "mit Faulenzen und Schlafen. Selbst\n",
                "sein Anblick macht bereits m\u00fcde."
            ]
        },
        "it": {
            "name": "SLAKOTH",
            "category": "Pok\u00e9mon Ozioso",
            "entry_text": [
                "Passa quasi tutto il tempo\n",
                "sdraiato. Soltanto a guardarlo\n",
                "si prova sonnolenza."
            ]
        },
        "es": {
            "name": "SLAKOTH",
            "category": "Pok\u00e9mon Gandul",
            "entry_text": [
                "Pasa la mayor parte del d\u00eda\n",
                "repanchingado. Entra sue\u00f1o\n",
                "solo de verlo."
            ]
        },
        "jp": {
            "name": "\u30ca\u30de\u30b1\u30ed",
            "category": "\u306a\u307e\u3051\u3082\u306e\u30dd\u30b1\u30e2\u30f3",
            "entry_text": [
                "\uff11\u306b\u3061\u306e\u3046\u3061\u3000\u307b\u3068\u3093\u3069\u306e\u3000\u3058\u304b\u3093\u3092\n",
                "\u306d\u3053\u308d\u304c\u3063\u3066\u3000\u3059\u3054\u3059\u3002\u305d\u306e\u3000\u3088\u3046\u3059\u3092\n",
                "\u307f\u3066\u3044\u308b\u3068\u3000\u306d\u3080\u3051\u306b\u3000\u304a\u305d\u308f\u308c\u308b\u3002"
            ]
        }
    },
    "catching_show": {
        "pal_park_land_area": "PAL_PARK_AREA_LAND_NORTH_WEST",
        "pal_park_water_area": "PAL_PARK_AREA_WATER_NONE",
        "catching_points": 50,
        "rarity": 30,
        "unused": 1285
    }
}