{
    "base_stats": {
        "hp": 80,
        "attack": 85,
        "defense": 95,
        "speed": 25,
        "special_attack": 30,
        "special_defense": 30
    },
    "types": [
        "TYPE_GROUND",
        "TYPE_ROCK"
    ],
    "catch_rate": 120,
    "base_exp_reward": 135,
    "ev_yields": {
        "hp": 0,
        "attack": 0,
        "defense": 0,
        "speed": 0,
        "special_attack": 0,
        "special_defense": 0
    },
    "held_items": {
        "common": "ITEM_NONE",
        "rare": "ITEM_NONE"
    },
    "gender_ratio": "GENDER_RATIO_FEMALE_50",
    "hatch_cycles": 20,
    "base_friendship": 70,
    "exp_rate": "EXP_RATE_SLOW",
    "egg_groups": [
        "EGG_GROUP_MONSTER",
        "EGG_GROUP_FIELD"
    ],
    "abilities": [
        "ABILITY_RECKLESS",
        "ABILITY_SOLID_ROCK",
        "ABILITY_NONE"
    ],
    "safari_flee_rate": 0,
    "body_color": "MON_COLOR_GRAY",
    "flip_sprite": false,
    "learnset": {
        "by_level": [
            [
                1,
                "MOVE_HORN_ATTACK"
            ],
            [
                1,
                "MOVE_TAIL_WHIP"
            ],
            [
                5,
                "MOVE_SCARY_FACE"
            ],
            [
                9,
                "MOVE_ENDEAVOR"
            ],
            [
                10,
                "MOVE_ROCK_TOMB"
            ],
            [
                12,
                "MOVE_ROCK_BLAST"
            ],
            [
                16,
                "MOVE_BULLDOZE"
            ],
            [
                21,
                "MOVE_STOMP"
            ],
            [
                25,
                "MOVE_HEADBUTT"
            ],
            [
                29,
                "MOVE_DRILL_RUN"
            ]
        ],
        "by_tm": [],
        "by_tutor": []
    },
    "evolutions": [
        [
            "EVO_LEVEL",
            34,
            "SPECIES_RHYDON"
        ]
    ],
    "footprint": {
        "has": true,
        "size": "FOOTPRINT_MEDIUM"
    },
    "pokedex_data": {
        "height": 10,
        "weight": 1150,
        "body_shape": "SHAPE_QUADRUPED",
        "trainer_scale_f": 272,
        "pokemon_scale_f": 236,
        "trainer_scale_m": 256,
        "pokemon_scale_m": 236,
        "trainer_pos_f": 8,
        "pokemon_pos_f": 16,
        "trainer_pos_m": 9,
        "pokemon_pos_m": 16,
        "en": {
            "name": "RHYHORN",
            "category": "Spikes Pok\u00e9mon",
            "entry_text": [
                "Its powerful tackles can destroy\n",
                "anything. However, it is too\n",
                "slow witted to help people work."
            ]
        },
        "fr": {
            "name": "RHINOCORNE",
            "category": "Pok\u00e9mon Piquant",
            "entry_text": [
                "Sa peau est tr\u00e8s \u00e9paisse et sa \n",
                "charge peut d\u00e9truire un immeuble.\n",
                "Dommage qu\u2019il soit stupide."
            ]
        },
        "de": {
            "name": "RIHORN",
            "category": "Stachler",
            "entry_text": [
                "Sein K\u00f6rper ist von einer dicken\n",
                "Haut umgeben und es kann wackelige\n",
                "Geb\u00e4ude zum Einsturz bringen."
            ]
        },
        "it": {
            "name": "RHYHORN",
            "category": "Pok\u00e9mon Punzoni",
            "entry_text": [
                "Ha una pelle molto spessa ed \u00e8 in\n",
                "grado di abbattere interi edifici.\n",
                "Non \u00e8 molto sagace."
            ]
        },
        "es": {
            "name": "RHYHORN",
            "category": "Pok\u00e9mon Clavos",
            "entry_text": [
                "Su cuerpo est\u00e1 protegido por una\n",
                "gruesa piel. Puede derribar hasta\n",
                "edificios, pero no es muy listo."
            ]
        },
        "jp": {
            "name": "\u30b5\u30a4\u30db\uff0d\u30f3",
            "category": "\u3068\u3052\u3068\u3052\u30dd\u30b1\u30e2\u30f3",
            "entry_text": [
                "\u304b\u305f\u3044\u3000\u3072\u3075\u3067\u3000\u304a\u304a\u308f\u308c\u305f\u3000\u304b\u3089\u3060\u3002\n",
                "\u305f\u3044\u3042\u305f\u308a\u3067\u3000\u30d3\u30eb\u3082\u3000\u305f\u304a\u3059\u3002\n",
                "\u3056\u3093\u306d\u3093\u306a\u304c\u3089\u3000\u3042\u305f\u307e\u306f\u3000\u308f\u308b\u3044\u3002"
            ]
        }
    },
    "catching_show": {
        "pal_park_land_area": "PAL_PARK_AREA_LAND_NORTH_EAST",
        "pal_park_water_area": "PAL_PARK_AREA_WATER_NONE",
        "catching_points": 50,
        "rarity": 30,
        "unused": 2824
    }
}